README.md
setup.py
amlearn/__init__.py
amlearn/_version.py
amlearn.egg-info/PKG-INFO
amlearn.egg-info/SOURCES.txt
amlearn.egg-info/dependency_links.txt
amlearn.egg-info/not-zip-safe
amlearn.egg-info/requires.txt
amlearn.egg-info/top_level.txt
amlearn/featurize/src/boop.f90
amlearn/featurize/src/distance_nn.f90
amlearn/featurize/src/distance_stats.f90
amlearn/featurize/src/mro_stats.f90
amlearn/featurize/src/neighbor_data.f90
amlearn/featurize/src/utils.f90
amlearn/featurize/src/voronoi_nn.f90
amlearn/featurize/src/voronoi_stats.f90
amlearn/featurize/__init__.py
amlearn/featurize/base.py
amlearn/featurize/medium_range_order.py
amlearn/featurize/nearest_neighbor.py
amlearn/featurize/pipeline.py
amlearn/featurize/short_range_order.py
amlearn/featurize/symmetry_function.py
amlearn/featurize/src/__init__.py
amlearn/featurize/tests/__init__.py
amlearn/featurize/tests/test_featurizer_pipeline.py
amlearn/featurize/tests/test_medium_range_order.py
amlearn/featurize/tests/test_nearest_neighbor.py
amlearn/featurize/tests/test_short_range_order.py
amlearn/featurize/tests/test_symmetry_function.py
amlearn/learn/__init__.py
amlearn/learn/base.py
amlearn/learn/classifier.py
amlearn/learn/predict.py
amlearn/learn/preprocessor.py
amlearn/learn/regressor.py
amlearn/learn/sklearn_patch/__init__.py
amlearn/learn/sklearn_patch/_split.py
amlearn/learn/sklearn_patch/_validation.py
amlearn/learn/tests/__init__.py
amlearn/learn/tests/test_classifier.py
amlearn/utils/PTE.json
amlearn/utils/__init__.py
amlearn/utils/amlearn_logging.yaml
amlearn/utils/backend.py
amlearn/utils/basetest.py
amlearn/utils/check.py
amlearn/utils/data.py
amlearn/utils/default_environment.yaml
amlearn/utils/directory.py
amlearn/utils/logging.py
amlearn/utils/packing.py
amlearn/utils/verbose.py
amlearn/utils/tests/__init__.py
amlearn/utils/tests/test_backend.py
amlearn/utils/tests/test_data.py
scripts/__init__.py
scripts/classification.py
scripts/distribution.py
scripts/feature_violinplot.py
scripts/featurize_bp_symmfunc.py
scripts/featurize_interstice.py
scripts/fractal_analysis.py
scripts/generalization.py
scripts/pdp_plot.py
scripts/regression.py