Metadata-Version: 1.1
Name: amlearn
Version: 0.3.4
Summary: Machine Learning package for amorphous materials.
Home-page: https://github.com/Qi-max/amlearn
Author: Qi Wang
Author-email: qwang.mse@gmail.com
License: modified BSD
Download-URL: https://github.com/Qi-max/amlearn/archive/0.1.0.tar.gz
Keywords: amorphous materials,Materials Genome Initiative,machine learning,data science,data mining,AI,artificial intelligence,featurizer,auto featurizerauto machine learning
Platform: UNKNOWN
Classifier: Intended Audience :: Science/Research
Classifier: Intended Audience :: Developers
Classifier: Programming Language :: Python
Classifier: Programming Language :: Fortran
Classifier: Programming Language :: Python :: 2
Classifier: Programming Language :: Python :: 2.7
Classifier: Programming Language :: Python :: 3
Classifier: Programming Language :: Python :: 3.4
Classifier: Programming Language :: Python :: 3.5
Classifier: Programming Language :: Python :: 3.6
Classifier: Topic :: Scientific/Engineering :: Artificial Intelligence
